{
    "studioName": "Green Yoga P-Berg",
    "contactName": "Srikanth Reddy Beeram",
    "address": {
        "street": "Sredzkistr. 59",
        "zip": "10405",
        "city": "Berlin",
        "url": "https://goo.gl/maps/87LAAiKgWsxpH5b46"
    },
    "tel1": {
        "number": "+49 1771 431355",
        "url": "tel:49-1771431355"
        },
    "whatsapp": {
        "number": "+49 1578 1974844",
        "url": "https://wa.me/00491771431355"
    },
    "socialMedia": {
        "facebook": "https://www.facebook.com/greenyoga.org",
        "instagram": "https://www.instagram.com/greenyoga.co/"
    } 
}